Metadata-Version: 2.1
Name: mmtester
Version: 0.5.0
Summary: Local tester for Topcoder Marathons & AtCoder Heuristic Contests
Home-page: https://github.com/FakePsyho/mmtester
Author: Psyho
License: MIT
Keywords: Topcoder,Marathon,AtCoder,Tester
Platform: UNKNOWN
Classifier: Development Status :: 3 - Alpha
Classifier: Intended Audience :: Developers
Classifier: Topic :: Scientific/Engineering
Classifier: Environment :: Console
Classifier: License :: OSI Approved :: MIT License
Classifier: Operating System :: OS Independent
Classifier: Programming Language :: Python :: 3
License-File: LICENSE
